snakecan/__main__.py
snakecan/basecommand.py
snakecan/cat.py
snakecan/ls.py
snakecan/main.py
snakecan/mkdir.py
snakecan/mv.py
snakecan/util.py
snakecan-0.0.0.dist-info/LICENSE
snakecan-0.0.0.dist-info/METADATA
snakecan-0.0.0.dist-info/WHEEL
snakecan-0.0.0.dist-info/top_level.txt
snakecan-0.0.0.dist-info/RECORD
