Metadata-Version: 2.1
Name: snakecan
Version: 0.0.0
Summary: A subset of UNIX utilities
Author-email: OzxyBox <kieferstashu@gmail.com>
Project-URL: Homepage, https://github.com/ozxybox/snakecan
Project-URL: Bug Tracker, https://github.com/ozxybox/snakecan/issues
Classifier: Programming Language :: Python :: 3.10
Classifier: Programming Language :: Python :: 3.11
Classifier: Programming Language :: Python :: 3 :: Only
Classifier: License :: OSI Approved :: MIT License
Classifier: Operating System :: OS Independent
Requires-Python: >=3.10
License-File: LICENSE
